pycolRxC/__init__.py
pycolRxC/_nb_utils.py
pycolRxC/_stat.py
pycolrxc-0.2.0.dist-info/licenses/COPYING
pycolrxc-0.2.0.dist-info/METADATA
pycolrxc-0.2.0.dist-info/WHEEL
pycolrxc-0.2.0.dist-info/top_level.txt
pycolrxc-0.2.0.dist-info/RECORD
