Metadata-Version: 2.4
Name: pycolRxC
Version: 0.2.0
Summary: A Python implementation of the ecolRxC algorithm
Author: Guilherme Calé
Author-email: guicale@posteo.net
License: GPL-2.0-or-later
License-File: COPYING
Requires-Dist: numpy
Requires-Dist: numba
Requires-Dist: pandas
Requires-Dist: seaborn
Requires-Dist: scipy<=1.15.3
Dynamic: license-file
